AKAgeCalculator/__init__.py
AKAgeCalculator/calculator.py
AKBMICalculator/__init__.py
AKBMICalculator/calculator.py
AKBAgeCalculator-0.0.1.dist-info/LICENSE
AKBAgeCalculator-0.0.1.dist-info/METADATA
AKBAgeCalculator-0.0.1.dist-info/WHEEL
AKBAgeCalculator-0.0.1.dist-info/top_level.txt
AKBAgeCalculator-0.0.1.dist-info/RECORD
