Metadata-Version: 2.1
Name: AKBAgeCalculator
Version: 0.0.1
Summary: Age_calculator
Home-page: https://github.com/ak8893893/python-upload-pip
Author: AK
Author-email: ak8893893@yahoo.com.tw
Classifier: Programming Language :: Python :: 3
Classifier: License :: OSI Approved :: MIT License
Classifier: Operating System :: OS Independent
Requires-Python: >=3.6
License-File: LICENSE
